magwords/__init__.py
magwords/engine.py
magwords/core/__init__.py
magwords/core/charset.py
magwords/core/decomposer.py
magwords/core/magtypes.py
magwords/gl/__init__.py
magwords/gl/shader.py
magwords/platform/__init__.py
magwords/platform/monitor/__init__.py
magwords/platform/monitor/glfw.py
magwords/platform/path/__init__.py
magwords/platform/path/darwin.py
magwords/platform/path/font_path.py
magwords/platform/path/fontfamily.py
magwords/platform/path/linux.py
magwords/platform/path/windows.py
magwords/shaders/base.frag
magwords/shaders/base.vert
magwords/shaders/bezier.frag
magwords/shaders/bezier.vert
magwords-1.0.0a2.dist-info/LICENSE
magwords-1.0.0a2.dist-info/METADATA
magwords-1.0.0a2.dist-info/WHEEL
magwords-1.0.0a2.dist-info/top_level.txt
magwords-1.0.0a2.dist-info/RECORD
