Metadata-Version: 2.1
Name: magwords
Version: 1.0.0a2
Summary: text-rendering library for OpenGL context
Home-page: https://github.com/asuka1975/magwords
Author: asuka1975
Author-email: asuka197512@gmail.com
License: MIT
Keywords: OpenGL FreeType2 TextRendering
Classifier: License :: OSI Approved :: MIT License
Classifier: Programming Language :: Python :: 3.9
License-File: LICENSE
Requires-Dist: cu2qu
Requires-Dist: freetype-py
Requires-Dist: glfw
Requires-Dist: numpy
Requires-Dist: PyGLM
Requires-Dist: PyOpenGL
Requires-Dist: scipy
